[

    {
        "Id": 15392480,
        "Title": "SQL语言简单分类整理",
        "DateAdded": "2021-10-11T11:10:00",
        "SourceUrl": null,
        "PostType": "BlogPost",
        "Body": "<p><img src=\"https://img2020.cnblogs.com/blog/2337411/202110/2337411-20211011110952198-970297782.png\" alt=\"\" loading=\"lazy\" /></p>\n<p>&nbsp;</p>",
        "BlogId": 675427,
        "Description": "",
        "DateUpdated": "2021-10-11T11:10:00",
        "IsMarkdown": false,
        "EntryName": null,
        "CreatedTime": "2021-10-11T11:10:08.893",
        "IsActive": true,
        "AutoDesc": "",
        "AccessPermission": "Anonymous",
        "DomainEvents": null
      }
]